mfd_network_adapter/__init__.py
mfd_network_adapter/const.py
mfd_network_adapter/data_structures.py
mfd_network_adapter/exceptions.py
mfd_network_adapter/poolmon.py
mfd_network_adapter/poolmon_const.py
mfd_network_adapter/api/__init__.py
mfd_network_adapter/api/basic/__init__.py
mfd_network_adapter/api/basic/linux.py
mfd_network_adapter/api/basic/windows.py
mfd_network_adapter/api/link/__init__.py
mfd_network_adapter/api/link/esxi.py
mfd_network_adapter/api/utils/__init__.py
mfd_network_adapter/api/utils/esxi.py
mfd_network_adapter/api/utils/freebsd.py
mfd_network_adapter/api/vlan/__init__.py
mfd_network_adapter/api/vlan/esxi.py
mfd_network_adapter/network_adapter_owner/__init__.py
mfd_network_adapter/network_adapter_owner/base.py
mfd_network_adapter/network_adapter_owner/data_structures.py
mfd_network_adapter/network_adapter_owner/esxi.py
mfd_network_adapter/network_adapter_owner/exceptions.py
mfd_network_adapter/network_adapter_owner/freebsd.py
mfd_network_adapter/network_adapter_owner/ipu_interface.py
mfd_network_adapter/network_adapter_owner/linux.py
mfd_network_adapter/network_adapter_owner/linux_ipu.py
mfd_network_adapter/network_adapter_owner/windows.py
mfd_network_adapter/network_adapter_owner/feature/__init__.py
mfd_network_adapter/network_adapter_owner/feature/ans/__init__.py
mfd_network_adapter/network_adapter_owner/feature/ans/base.py
mfd_network_adapter/network_adapter_owner/feature/ans/data_structures.py
mfd_network_adapter/network_adapter_owner/feature/ans/windows.py
mfd_network_adapter/network_adapter_owner/feature/arp/__init__.py
mfd_network_adapter/network_adapter_owner/feature/arp/base.py
mfd_network_adapter/network_adapter_owner/feature/arp/esxi.py
mfd_network_adapter/network_adapter_owner/feature/arp/freebsd.py
mfd_network_adapter/network_adapter_owner/feature/arp/linux.py
mfd_network_adapter/network_adapter_owner/feature/arp/windows.py
mfd_network_adapter/network_adapter_owner/feature/base/__init__.py
mfd_network_adapter-14.4.1.dist-info/licenses/AUTHORS.md
mfd_network_adapter-14.4.1.dist-info/licenses/LICENSE.md
mfd_network_adapter-14.4.1.dist-info/METADATA
mfd_network_adapter-14.4.1.dist-info/WHEEL
mfd_network_adapter-14.4.1.dist-info/top_level.txt
mfd_network_adapter-14.4.1.dist-info/RECORD
