Metadata-Version: 2.4
Name: mfd-network-adapter
Version: 14.4.1
Summary: Module which handle operations on network adapters installed on different operating systems
Project-URL: Homepage, https://github.com/intel/mfd
Project-URL: Repository, https://github.com/intel/mfd-network-adapter
Project-URL: Issues, https://github.com/intel/mfd-network-adapter/issues
Project-URL: Changelog, https://github.com/intel/mfd-network-adapter/blob/main/CHANGELOG.md
Requires-Python: <3.14,>=3.10
License-File: LICENSE.md
License-File: AUTHORS.md
Requires-Dist: funcy>=1.17
Requires-Dist: mfd-cli-client<2,>=1.11.0
Requires-Dist: mfd-common-libs<2,>=1.11.0
Requires-Dist: mfd-connect<8,>=7.12.0
Requires-Dist: mfd-const<1,>=0.23.0
Requires-Dist: mfd-dcb<2,>=1.18.0
Requires-Dist: mfd-dmesg<2,>=1.20.0
Requires-Dist: mfd-ethtool<4,>=3.14.0
Requires-Dist: mfd-event-log<1,>=0.9.0
Requires-Dist: mfd-kernel-namespace<2,>=1.8.0
Requires-Dist: mfd-model[config]<1,>=0.9.0
Requires-Dist: mfd-package-manager<4,>=3.0.0
Requires-Dist: mfd-sysctl<2,>=1.6.0
Requires-Dist: mfd-typing<2,>=1.24.0
Requires-Dist: mfd-win-registry<2,>=1.17.0
Requires-Dist: mfd_libibverbs_utils<2,>=1.6.0
Requires-Dist: mfd_packet_capture<3,>=2.16.0
Requires-Dist: netaddr>=0.8.0
Requires-Dist: pyyaml>=6.0
Dynamic: license-file
